function_schema/__init__.py
function_schema/cli.py
function_schema/core.py
function_schema/types.py
function_schema/utils.py
function_schema-0.4.5.dist-info/entry_points.txt
function_schema-0.4.5.dist-info/WHEEL
function_schema-0.4.5.dist-info/METADATA
function_schema-0.4.5.dist-info/RECORD
