Metadata-Version: 2.3
Name: function-schema
Version: 0.4.5
Summary: A small utility to generate JSON schemas for python functions.
Keywords: json-schema,function,documentation,openai,utility
Author-email: Changkyun Kim <comfuture@gmail.com>
Maintainer-email: Changkyun Kim <comfuture@gmail.com>
Requires-Python: >= 3.9
Classifier: Development Status :: 3 - Alpha
Classifier: Programming Language :: Python :: 3.9
Project-URL: Homepage, https://github.com/comfuture/function-schema
Project-URL: Repository, https://github.com/comfuture/function-schema
